restricted_countries/__init__.py
restricted_countries/apps.py
restricted_countries/middleware.py
restricted_countries/settings.py
restricted_countries/utils.py
django_restricted_countries-0.1.2.dist-info/LICENSE
django_restricted_countries-0.1.2.dist-info/METADATA
django_restricted_countries-0.1.2.dist-info/WHEEL
django_restricted_countries-0.1.2.dist-info/top_level.txt
django_restricted_countries-0.1.2.dist-info/RECORD
