Metadata-Version: 2.2
Name: django-restricted-countries
Version: 0.1.2
Summary: Django middleware to restrict access based on the client's country
Home-page: https://github.com/Mbulelo-Peyi/restricted_countries
Author: Mbulelo Phillip Peyi
Author-email: your.email@example.com
Keywords: django,restricted access,web,country,logging
Classifier: Programming Language :: Python :: 3
Classifier: Framework :: Django
Classifier: License :: OSI Approved :: MIT License
Classifier: Operating System :: OS Independent
Requires-Python: >=3.6
License-File: LICENSE
Requires-Dist: Django>=3.1
Requires-Dist: geoip2>=4.0
Requires-Dist: python-ipware>=2.1
Dynamic: author
Dynamic: author-email
Dynamic: classifier
Dynamic: description
Dynamic: description-content-type
Dynamic: home-page
Dynamic: keywords
Dynamic: requires-dist
Dynamic: requires-python
Dynamic: summary
